Bitcoin_module/__init__.py
Bitcoin_module/bitcoin_notification.py
bitcoin_notification_python_fariya_banu-1.0.1.dist-info/LICENSE
bitcoin_notification_python_fariya_banu-1.0.1.dist-info/METADATA
bitcoin_notification_python_fariya_banu-1.0.1.dist-info/WHEEL
bitcoin_notification_python_fariya_banu-1.0.1.dist-info/top_level.txt
bitcoin_notification_python_fariya_banu-1.0.1.dist-info/RECORD
