Metadata-Version: 2.1
Name: bitcoin-notification-python-fariya-banu
Version: 1.0.1
Summary: BITCOIN PRICE NOTIFICATION PROJECT
Home-page: https://github.com/fariya-banu234-au7/python_project
Author: FARIYA BANU
Author-email: fariyabanu234@gmail.com
License: UNKNOWN
Platform: UNKNOWN
Classifier: Programming Language :: Python :: 3
Classifier: License :: OSI Approved :: MIT License
Classifier: Operating System :: OS Independent
Requires-Python: >=3.6
